quantum_jit/__init__.py
quantum_jit/core.py
quantum_jit/benchmarking/__init__.py
quantum_jit/benchmarking/benchmarker.py
quantum_jit/circuit_generation/__init__.py
quantum_jit/circuit_generation/circuit_generator.py
quantum_jit/circuit_generation/circuit_optimizer.py
quantum_jit/decision/__init__.py
quantum_jit/decision/decision_maker.py
quantum_jit/implementations/__init__.py
quantum_jit/implementations/analyzer.py
quantum_jit/implementations/binary_function.py
quantum_jit/implementations/fourier_transform.py
quantum_jit/implementations/matrix_multiply.py
quantum_jit/implementations/optimization.py
quantum_jit/implementations/search.py
quantum_jit/implementations/selector.py
quantum_jit/patterns/__init__.py
quantum_jit/patterns/base_detector.py
quantum_jit/patterns/common_patterns.py
quantum_jit/patterns/core.py
quantum_jit/patterns/function_analyzer.py
quantum_jit/patterns/detectors/__init__.py
quantum_jit/patterns/detectors/algorithms.py
quantum_jit/patterns/detectors/basic.py
quantum_jit/patterns/detectors/cryptography.py
quantum_jit/patterns/detectors/graph.py
quantum_jit/patterns/detectors/machine_learning.py
quantum_jit/patterns/detectors/optimization.py
quantum_jit/patterns/detectors/simulation.py
quantum_jit/runtime/__init__.py
quantum_jit/runtime/backends.py
quantum_jit/runtime/circuit_cache.py
quantum_jit/runtime/execution_manager.py
quantum_jit/runtime/result_processor.py
quantum_jit/visualization/__init__.py
quantum_jit/visualization/call_graph.py
quantum_jit/visualization/code_annotator.py
quantum_jit/visualization/pattern_dashboard.py
quantum_jit/visualization/performance_tracker.py
qopy_patch-0.1.0.dist-info/METADATA
qopy_patch-0.1.0.dist-info/WHEEL
qopy_patch-0.1.0.dist-info/top_level.txt
qopy_patch-0.1.0.dist-info/RECORD
