Metadata-Version: 2.4
Name: qopy-patch
Version: 0.1.0
Summary: An example library for quantum copy and patch jit
Author-email: James Munsch <james.a.munsch@gmail.com>
Requires-Python: >=3.13
Requires-Dist: dill>=0.3.9
Requires-Dist: networkx>=3.4.2
Requires-Dist: numpy>=2.2.0
Requires-Dist: pandas>=2.2.3
Requires-Dist: qiskit>=1.4.0
Requires-Dist: qiskit-aer>=0.17.0
Requires-Dist: seaborn>=0.13.2
Provides-Extra: dev
Requires-Dist: pytest>=8.3.0; extra == "dev"
Requires-Dist: pytest-cov>=4.1.0; extra == "dev"
Provides-Extra: test
Requires-Dist: pytest>=8.3.0; extra == "test"
Requires-Dist: pytest-cov>=4.1.0; extra == "test"
Provides-Extra: all
Requires-Dist: numpy>=2.2.0; extra == "all"
Requires-Dist: qiskit>=1.4.0; extra == "all"
Requires-Dist: qiskit-aer>=0.17.0; extra == "all"
Requires-Dist: pytest>=8.3.0; extra == "all"
Requires-Dist: pytest-cov>=4.1.0; extra == "all"
Requires-Dist: matplotlib>=3.10.0; extra == "all"
